pantos/cli/__init__.py
pantos/cli/__main__.py
pantos/cli/application.py
pantos/cli/configuration.py
pantos/cli/exceptions.py
pantos/client-cli.env
pantos/client-cli.yml
pantos/client-library.env
pantos/client-library.yml
pantos_client_cli-1.1.2.dist-info/LICENSE.md
pantos_client_cli-1.1.2.dist-info/WHEEL
pantos_client_cli-1.1.2.dist-info/entry_points.txt
pantos_client_cli-1.1.2.dist-info/RECORD
pantos_client_cli-1.1.2.dist-info/METADATA
