Metadata-Version: 2.1
Name: pantos-client-cli
Version: 1.1.2
Summary: Client CLI for engaging with the Pantos system
License: GPL-3.0-only
Author: Pantos GmbH
Author-email: contact@pantos.io
Requires-Python: >=3.10,<4.0
Classifier: License :: OSI Approved :: GNU General Public License v3 (GPLv3)
Classifier: Programming Language :: Python :: 3
Classifier: Programming Language :: Python :: 3.10
Classifier: Programming Language :: Python :: 3.11
Classifier: Programming Language :: Python :: 3.12
Requires-Dist: pantos-common (==2.1.2) ; python_version >= "3.10" and python_version < "4.0"
Requires-Dist: pantos-client-library (==1.1.4) ; python_version >= "3.10" and python_version < "4.0"
Requires-Dist: cerberus (==1.3.4) ; python_version >= "3.10" and python_version < "4.0"
Requires-Dist: pyyaml (==6.0.1) ; python_version >= "3.10" and python_version < "4.0"
Requires-Dist: requests (==2.32.3) ; python_version >= "3.10" and python_version < "4.0"
Requires-Dist: web3 (==6.5.0) ; python_version >= "3.10" and python_version < "4.0"
Requires-Dist: pyaml-env (==1.2.1) ; python_version >= "3.10" and python_version < "4.0"
Requires-Dist: python-dotenv (==1.0.1) ; python_version >= "3.10" and python_version < "4.0"
Requires-Dist: aiohttp (==3.9.5) ; python_version >= "3.10" and python_version < "4.0"
Requires-Dist: aiosignal (==1.3.1) ; python_version >= "3.10" and python_version < "4.0"
Requires-Dist: amqp (==5.2.0) ; python_version >= "3.10" and python_version < "4.0"
Requires-Dist: aniso8601 (==9.0.1) ; python_version >= "3.10" and python_version < "4.0"
Requires-Dist: annotated-types (==0.7.0) ; python_version >= "3.10" and python_version < "4"
Requires-Dist: async-timeout (==4.0.3) ; python_version >= "3.10" and python_version < "3.11"
Requires-Dist: attrs (==23.2.0) ; python_version >= "3.10" and python_version < "4.0"
Requires-Dist: billiard (==4.2.0) ; python_version >= "3.10" and python_version < "4.0"
Requires-Dist: bitarray (==2.9.2) ; python_version >= "3.10" and python_version < "4"
Requires-Dist: blinker (==1.8.2) ; python_version >= "3.10" and python_version < "4.0"
Requires-Dist: celery (==5.3.1) ; python_version >= "3.10" and python_version < "4.0"
Requires-Dist: certifi (==2024.7.4) ; python_version >= "3.10" and python_version < "4.0"
Requires-Dist: charset-normalizer (==3.3.2) ; python_version >= "3.10" and python_version < "4.0"
Requires-Dist: ckzg (==1.0.2) ; python_version >= "3.10" and python_version < "4"
Requires-Dist: click (==8.1.7) ; python_version >= "3.10" and python_version < "4.0"
Requires-Dist: click-didyoumean (==0.3.1) ; python_version >= "3.10" and python_version < "4.0"
Requires-Dist: click-plugins (==1.1.1) ; python_version >= "3.10" and python_version < "4.0"
Requires-Dist: click-repl (==0.3.0) ; python_version >= "3.10" and python_version < "4.0"
Requires-Dist: colorama (==0.4.6) ; python_version >= "3.10" and python_version < "4.0" and platform_system == "Windows"
Requires-Dist: cytoolz (==0.12.3) ; python_version >= "3.10" and python_version < "4" and implementation_name == "cpython"
Requires-Dist: eth-abi (==5.1.0) ; python_version >= "3.10" and python_version < "4"
Requires-Dist: eth-account (==0.13.0) ; python_version >= "3.10" and python_version < "4"
Requires-Dist: eth-hash (==0.7.0) ; python_version >= "3.10" and python_version < "4"
Requires-Dist: eth-keyfile (==0.8.1) ; python_version >= "3.10" and python_version < "4"
Requires-Dist: eth-keys (==0.4.0) ; python_version >= "3.10" and python_version < "4"
Requires-Dist: eth-rlp (==2.1.0) ; python_version >= "3.10" and python_version < "4"
Requires-Dist: eth-typing (==3.5.2) ; python_version >= "3.10" and python_version < "4"
Requires-Dist: eth-utils (==2.3.1) ; python_version >= "3.10" and python_version < "4"
Requires-Dist: flask (==3.0.3) ; python_version >= "3.10" and python_version < "4.0"
Requires-Dist: flask-restful (==0.3.10) ; python_version >= "3.10" and python_version < "4.0"
Requires-Dist: frozenlist (==1.4.1) ; python_version >= "3.10" and python_version < "4.0"
Requires-Dist: hexbytes (==1.2.1) ; python_version >= "3.10" and python_version < "4"
Requires-Dist: idna (==3.7) ; python_version >= "3.10" and python_version < "4.0"
Requires-Dist: itsdangerous (==2.2.0) ; python_version >= "3.10" and python_version < "4.0"
Requires-Dist: jinja2 (==3.1.4) ; python_version >= "3.10" and python_version < "4.0"
Requires-Dist: json-log-formatter (==0.5.2) ; python_version >= "3.10" and python_version < "4.0"
Requires-Dist: jsonschema (==4.23.0) ; python_version >= "3.10" and python_version < "4.0"
Requires-Dist: jsonschema-specifications (==2023.12.1) ; python_version >= "3.10" and python_version < "4.0"
Requires-Dist: kombu (==5.3.7) ; python_version >= "3.10" and python_version < "4.0"
Requires-Dist: lru-dict (==1.3.0) ; python_version >= "3.10" and python_version < "4.0"
Requires-Dist: markupsafe (==2.1.5) ; python_version >= "3.10" and python_version < "4.0"
Requires-Dist: multidict (==6.0.5) ; python_version >= "3.10" and python_version < "4.0"
Requires-Dist: parsimonious (==0.10.0) ; python_version >= "3.10" and python_version < "4"
Requires-Dist: prompt-toolkit (==3.0.47) ; python_version >= "3.10" and python_version < "4.0"
Requires-Dist: protobuf (==5.27.2) ; python_version >= "3.10" and python_version < "4.0"
Requires-Dist: pycryptodome (==3.20.0) ; python_version >= "3.10" and python_version < "4.0"
Requires-Dist: pydantic (==2.8.2) ; python_version >= "3.10" and python_version < "4"
Requires-Dist: pydantic-core (==2.20.1) ; python_version >= "3.10" and python_version < "4"
Requires-Dist: python-dateutil (==2.9.0.post0) ; python_version >= "3.10" and python_version < "4.0"
Requires-Dist: pytz (==2024.1) ; python_version >= "3.10" and python_version < "4.0"
Requires-Dist: pywin32 (==306) ; python_version >= "3.10" and python_version < "4.0" and platform_system == "Windows"
Requires-Dist: referencing (==0.35.1) ; python_version >= "3.10" and python_version < "4.0"
Requires-Dist: regex (==2024.5.15) ; python_version >= "3.10" and python_version < "4"
Requires-Dist: rlp (==3.0.0) ; python_version >= "3.10" and python_version < "4"
Requires-Dist: rpds-py (==0.19.0) ; python_version >= "3.10" and python_version < "4.0"
Requires-Dist: semantic-version (==2.10.0) ; python_version >= "3.10" and python_version < "4.0"
Requires-Dist: setuptools (==70.3.0) ; python_version >= "3.10" and python_version < "4.0"
Requires-Dist: six (==1.16.0) ; python_version >= "3.10" and python_version < "4.0"
Requires-Dist: toolz (==0.12.1) ; python_version >= "3.10" and python_version < "4" and (implementation_name == "pypy" or implementation_name == "cpython")
Requires-Dist: typing-extensions (==4.12.2) ; python_version >= "3.10" and python_version < "4"
Requires-Dist: tzdata (==2024.1) ; python_version >= "3.10" and python_version < "4.0"
Requires-Dist: urllib3 (==2.2.2) ; python_version >= "3.10" and python_version < "4.0"
Requires-Dist: vine (==5.1.0) ; python_version >= "3.10" and python_version < "4.0"
Requires-Dist: wcwidth (==0.2.13) ; python_version >= "3.10" and python_version < "4.0"
Requires-Dist: websockets (==12.0) ; python_version >= "3.10" and python_version < "4.0"
Requires-Dist: werkzeug (==3.0.3) ; python_version >= "3.10" and python_version < "4.0"
Requires-Dist: yarl (==1.9.4) ; python_version >= "3.10" and python_version < "4.0"
